molactivity/A10_final_array.py
molactivity/A11_final_asarray.py
molactivity/A12_layers.py
molactivity/A13_loss.py
molactivity/A14_model_save_load.py
molactivity/A15_module.py
molactivity/A16_operations.py
molactivity/A17_normalization.py
molactivity/A18_optimizer.py
molactivity/A19_prepare_data.py
molactivity/A1_activations.py
molactivity/A20_math.py
molactivity/A21_predict.py
molactivity/A22_random.py
molactivity/A23_strong_matmul.py
molactivity/A24_strong_reshape.py
molactivity/A25_strong_sqrt.py
molactivity/A26_tensor.py
molactivity/A27_tools.py
molactivity/A28_train.py
molactivity/A29_train_further.py
molactivity/A2_arrays.py
molactivity/A30_train_parallel.py
molactivity/A31_transformer.py
molactivity/A32_typing.py
molactivity/A33_eval_parallel.py
molactivity/A34_predict_parallel.py
molactivity/A3_autograd.py
molactivity/A4_chem_features.py
molactivity/A5_chem_utils.py
molactivity/A6_argument_parser.py
molactivity/A7_data_process.py
molactivity/A8_dropout.py
molactivity/A9_evaluate.py
molactivity/B10_predict.py
molactivity/B11_focal_loss.py
molactivity/B12_normalization.py
molactivity/B13_operations.py
molactivity/B14_optimizer.py
molactivity/B15_prepare_data.py
molactivity/B16_tensor.py
molactivity/B17_train.py
molactivity/B18_train_further.py
molactivity/B19_train_parallel.py
molactivity/B1_activations.py
molactivity/B20_predict_fast_parallel.py
molactivity/B2_arrays.py
molactivity/B3_autograd.py
molactivity/B4_dropout.py
molactivity/B5_evaluate.py
molactivity/B6_evaluate_fast_parallel.py
molactivity/B7_module.py
molactivity/B8_layers.py
molactivity/B9_transformer.py
molactivity/C1_evaluate_predict.py
molactivity/C2_train.py
molactivity/C3_utils.py
molactivity/C4_evaluate_predict_parallel.py
molactivity/C5_train_tools.py
molactivity/D1_config.py
molactivity/D2_data_loader.py
molactivity/D3_model.py
molactivity/D4_predict.py
molactivity/D5_train.py
molactivity/D6_evaluate_tools.py
molactivity/D7_predict_tools.py
molactivity/E1_structure_analysis.py
molactivity-3.0.dist-info/LICENSE
molactivity-3.0.dist-info/METADATA
molactivity-3.0.dist-info/WHEEL
molactivity-3.0.dist-info/entry_points.txt
molactivity-3.0.dist-info/top_level.txt
molactivity-3.0.dist-info/RECORD
